[
  {
    "api_list": [
      {
        "category_name": "DeveloperTools",
        "tool_name": "ipify",
        "api_name": "get_public_ip",
        "api_description": "Retrieve the user's public IPv4 or IPv6 address in plain text.",
        "required_parameters": [],
        "optional_parameters": [
          {
            "name": "format",
            "type": "ENUM",
            "description": "The response format: 'text', 'json', or 'jsonp'.",
            "default": "text"
          },
          {
            "name": "callback",
            "type": "STRING",
            "description": "The name of the JSONP callback function (used only when format is 'jsonp').",
            "default": ""
          }
        ],
        "method": "GET",
        "template_response": {
          "ip": "str"
        }
      },
      {
        "category_name": "DeveloperTools",
        "tool_name": "ipify",
        "api_name": "get_geolocation",
        "api_description": "Retrieve geolocation information based on the user's public IP address.",
        "required_parameters": [],
        "optional_parameters": [],
        "method": "GET",
        "template_response": {
          "ip": "str",
          "location": {
            "country": "str",
            "region": "str",
            "city": "str",
            "latitude": "float",
            "longitude": "float",
            "timezone": "str"
          }
        }
      }
    ],
    "query": "Find my public IP address and provide detailed geolocation information about it.",
    "relevant APIs": [],
    "query_id": 2
  }
]
