[
  {
    "api_list": [
      {
          "tool_name": "barter",
          "api_name": "get_app_settings",
          "api_description": "Get settings of a specific app by app_id.",
          "required_parameters": [
            {
              "name": "app_id",
              "type": "NUMBER",
              "description": "The app ID of the third-party application."
            }
          ],
          "method": "GET"
      },
      {
          "tool_name": "jokeapi",
          "api_name": "get_joke",
          "api_description": "Fetch jokes based on category, filters, and other parameters.",
          "optional_parameters": [
            {
              "name": "category",
              "type": "STRING",
              "description": "Joke category.",
              "default": "Any"
            },
            {
              "name": "amount",
              "type": "INTEGER",
              "description": "Number of jokes to fetch.",
              "default": 1
            }
          ],
          "method": "GET"
      }
    ],
    "query": "Can you tell me the settings of the app with app_id 123 on Barter, and also fetch a funny joke for me?",
    "relevant APIs": [],
    "query_id": 1
  },
  {
    "api_list": [
      {
          "tool_name": "barter",
          "api_name": "browse_cards",
          "api_description": "Browse all trading cards.",
          "required_parameters": [],
          "method": "GET"
      },
      {
          "tool_name": "jokeapi",
          "api_name": "get_joke_categories",
          "api_description": "Retrieve all available joke categories.",
          "required_parameters": [],
          "method": "GET"
      }
    ],
    "query": "Find all available trading cards on Barter.vg and tell me what joke categories are available on JokeAPI.",
    "relevant APIs": [],
    "query_id": 2
  },
  {
    "api_list": [
      {
          "tool_name": "barter",
          "api_name": "get_user",
          "api_description": "Get information about a user by their user_id.",
          "required_parameters": [
            {
              "name": "user_id",
              "type": "STRING",
              "description": "The hex ID of the barter.vg user."
            }
          ],
          "method": "GET"
      },
      {
          "tool_name": "jokeapi",
          "api_name": "get_flags",
          "api_description": "Retrieve available blacklist flags.",
          "required_parameters": [],
          "method": "GET"
      }
    ],
    "query": "I need to get the details of user 'a1b2c3' on Barter.vg, and also find out what blacklist flags are present in JokeAPI.",
    "relevant APIs": [],
    "query_id": 3
  },
  {
    "api_list": [
      {
          "tool_name": "barter",
          "api_name": "browse_dlc",
          "api_description": "Browse all downloadable content.",
          "required_parameters": [],
          "method": "GET"
      },
      {
          "tool_name": "jokeapi",
          "api_name": "get_supported_languages",
          "api_description": "Retrieve supported languages for jokes and system messages.",
          "required_parameters": [],
          "method": "GET"
      }
    ],
    "query": "Could you show me all the downloadable content available on Barter.vg? Also, list the supported languages for jokes on JokeAPI.",
    "relevant APIs": [],
    "query_id": 4
  }
]